orator/__init__.py
orator/commands/__init__.py
orator/commands/application.py
orator/commands/command.py
orator/commands/migrations/__init__.py
orator/commands/migrations/base_command.py
orator/commands/migrations/install_command.py
orator/commands/migrations/make_command.py
orator/commands/migrations/migrate_command.py
orator/commands/migrations/refresh_command.py
orator/commands/migrations/reset_command.py
orator/commands/migrations/rollback_command.py
orator/commands/migrations/status_command.py
orator/commands/models/__init__.py
orator/commands/models/make_command.py
orator/commands/models/stubs.py
orator/commands/seeds/__init__.py
orator/commands/seeds/base_command.py
orator/commands/seeds/make_command.py
orator/commands/seeds/seed_command.py
orator/connections/__init__.py
orator/connections/connection.py
orator/connections/connection_interface.py
orator/connections/connection_resolver_interface.py
orator/connections/mysql_connection.py
orator/connections/postgres_connection.py
orator/connections/sqlite_connection.py
orator/connectors/__init__.py
orator/connectors/connection_factory.py
orator/connectors/connector.py
orator/connectors/mysql_connector.py
orator/connectors/postgres_connector.py
orator/connectors/sqlite_connector.py
orator/database_manager.py
orator/dbal/__init__.py
orator/dbal/abstract_asset.py
orator/dbal/column.py
orator/dbal/column_diff.py
orator/dbal/comparator.py
orator/dbal/exceptions/__init__.py
orator/dbal/foreign_key_constraint.py
orator/dbal/identifier.py
orator/dbal/index.py
orator/dbal/mysql_schema_manager.py
orator/dbal/platforms/__init__.py
orator/dbal/platforms/keywords/__init__.py
orator/dbal/platforms/keywords/keyword_list.py
orator/dbal/platforms/keywords/mysql_keywords.py
orator/dbal/platforms/keywords/postgresql_keywords.py
orator/dbal/platforms/keywords/sqlite_keywords.py
orator/dbal/platforms/mysql57_platform.py
orator/dbal/platforms/mysql_platform.py
orator/dbal/platforms/platform.py
orator-0.9.8.dist-info/entry_points.txt
orator-0.9.8.dist-info/LICENSE
orator-0.9.8.dist-info/WHEEL
orator-0.9.8.dist-info/METADATA
orator-0.9.8.dist-info/RECORD
